munerator-0.23.0.data/data/local/munerator/static/index.html
munerator-0.23.0.data/data/local/munerator/static/.gitkeep
munerator-0.23.0.data/data/local/munerator/static/assets/arena-26fc4e924864d064f8ce5913e248feaa.css
munerator-0.23.0.data/data/local/munerator/static/assets/vendor-3d71feadea86918220f02708e70bb616.js
munerator-0.23.0.data/data/local/munerator/static/assets/arena-2467f262e4d2d923b1bc8cc00cd69764.js
munerator-0.23.0.data/data/local/munerator/static/assets/vendor-d41d8cd98f00b204e9800998ecf8427e.css
munerator-0.23.0.data/data/local/munerator/static/assets/headmodels/angelyss_blue.png
munerator-0.23.0.data/data/local/munerator/static/assets/headmodels/smarine_orange.png
munerator-0.23.0.data/data/local/munerator/static/assets/headmodels/skelebot_blue.png
munerator-0.23.0.data/data/local/munerator/static/assets/headmodels/sarge_indigo.png
munerator-0.23.0.data/data/local/munerator/static/assets/headmodels/penguin_red.png
munerator-0.23.0.data/data/local/munerator/static/assets/headmodels/kyonshi_blue.png
munerator-0.23.0.data/data/local/munerator/static/assets/headmodels/penguin_default.png
munerator-0.23.0.data/data/local/munerator/static/assets/headmodels/gargoyle_blue.png
munerator-0.23.0.data/data/local/munerator/static/assets/headmodels/kyonshi_default.png
munerator-0.23.0.data/data/local/munerator/static/assets/headmodels/gargoyle_tech.png
munerator-0.23.0.data/data/local/munerator/static/assets/headmodels/tony_default.png
munerator-0.23.0.data/data/local/munerator/static/assets/headmodels/skelebot_red.png
munerator-0.23.0.data/data/local/munerator/static/assets/headmodels/beret.png
munerator-0.23.0.data/data/local/munerator/static/assets/headmodels/liz_default.png
munerator-0.23.0.data/data/local/munerator/static/assets/headmodels/assassin.png
munerator-0.23.0.data/data/local/munerator/static/assets/headmodels/sarge.png
munerator-0.23.0.data/data/local/munerator/static/assets/headmodels/sarge_red.png
munerator-0.23.0.dist-info/METADATA
munerator-0.23.0.dist-info/dependency_links.txt
munerator-0.23.0.dist-info/RECORD
munerator-0.23.0.dist-info/WHEEL
munerator-0.23.0.dist-info/top_level.txt
munerator-0.23.0.dist-info/entry_points.txt
munerator-0.23.0.dist-info/DESCRIPTION.rst
munerator-0.23.0.dist-info/metadata.json
