Metadata-Version: 2.0
Name: munerator
Version: 0.23.0
Summary: Manager of OpenArena battles
Home-page: https://github.com/aequitas/munerator
Author: Johan Bloemberg
Author-email: mail@ijohan.nl
License: Copyright 2014 Johan Bloemberg
Requires-Dist: six
Requires-Dist: docopt
Requires-Dist: pyzmq
Requires-Dist: webcolors
Requires-Dist: python-Levenshtein
Requires-Dist: python-dateutil
Requires-Dist: rcfile
Requires-Dist: applib
Provides-Extra: db
Requires-Dist: mongoengine; extra == 'db'
Requires-Dist: eve (==0.5-dev); extra == 'db'
Requires-Dist: eve-mongoengine (==0.0.6-dev); extra == 'db'
Requires-Dist: flask; extra == 'db'
